norfs/__init__.py
norfs/client.py
norfs/filesystem.py
norfs/helpers.py
norfs/permissions.py
norfs/copy/__init__.py
norfs/copy/base.py
norfs/copy/local.py
norfs/copy/s3.py
norfs/fs/__init__.py
norfs/fs/base.py
norfs/fs/local.py
norfs/fs/memory.py
norfs/fs/s3.py
norfs-3.0.0.dist-info/LICENSE.txt
norfs-3.0.0.dist-info/METADATA
norfs-3.0.0.dist-info/WHEEL
norfs-3.0.0.dist-info/top_level.txt
norfs-3.0.0.dist-info/RECORD
