Metadata-Version: 2.1
Name: norfs
Version: 3.0.0
Summary: Normalized filesystem. This library offers a common interface to interact with multiple filesystems, local or remote.
Home-page: https://github.com/Galbar/norfs
Author: Alessio Linares
Author-email: alessio@alessio.cc
License: MIT
Download-URL: https://github.com/Galbar/norfs/archive/3.0.0.tar.gz
Project-URL: Documentation, https://galbar.github.io/norfs
Project-URL: Source, https://github.com/Galbar/norfs
Keywords: filesystem boto s3 file directory norfs
Platform: UNKNOWN
Classifier: Development Status :: 5 - Production/Stable
Classifier: Intended Audience :: Developers
Classifier: Topic :: Software Development :: Libraries
Classifier: License :: OSI Approved :: MIT License
Classifier: Programming Language :: Python :: 3
Classifier: Programming Language :: Python :: 3.6
Requires-Python: >=3.6
